scrape_reviews/__init__.py
scrape_reviews/categories_of_interest.py
scrape_reviews/cleaning_gmaps.py
scrape_reviews/connect_with_sqlite_db.py
scrape_reviews/gmaps_constants.py
scrape_reviews/saving.py
scrape_reviews/scraping_gmaps.py
scrape_reviews-0.5.1.dist-info/LICENSE
scrape_reviews-0.5.1.dist-info/METADATA
scrape_reviews-0.5.1.dist-info/WHEEL
scrape_reviews-0.5.1.dist-info/top_level.txt
scrape_reviews-0.5.1.dist-info/RECORD
