Metadata-Version: 2.1
Name: scrape-reviews
Version: 0.5.1
Summary: Scrape Online Reviews
Home-page: https://github.com/voulkon/scrape_reviews
Author: Konstantinos Voulgaropoulos
Author-email: voulkon93@gmail.com
Project-URL: Source Code, https://github.com/voulkon/scrape_reviews
Keywords: scrape,reviews,maps,google,gmaps,hotels,restaurants,hotel_reviews,restaurant_reviews
Classifier: Programming Language :: Python :: 3
Classifier: License :: OSI Approved :: MIT License
Classifier: Operating System :: OS Independent
Requires-Python: >=3.9
License-File: LICENSE
Requires-Dist: pandas
Requires-Dist: webdriver-manager (==3.8.3)
Requires-Dist: selenium (>=4.1.0)
